[
	{
		"name": "grass",
		"list": [
			{
				"path": "sounds/grass/1.mp3",
				"weight": 1
			},
			{
				"path": "sounds/grass/2.mp3",
				"weight": 1
			}
		],
		"playback_mode": 0,
		"random_pitch": 1.2,
		"random_volume_offset_db": 3,
		"max_db": 3
	},
	{
		"fork": true,
		"name": "grass_placeDestroy",
		"volume_db": 3,
		"max_db": 10
	},
	
	
	{
		"name": "stone",
		"list": [
			{
				"path": "sounds/stone/1.mp3",
				"weight": 1
			},
			{
				"path": "sounds/stone/2.mp3",
				"weight": 1
			},
			{
				"path": "sounds/stone/3.mp3",
				"weight": 1
			}
		],
		"playback_mode": 0,
		"random_pitch": 1.2,
		"random_volume_offset_db": 3,
		"max_db": 3
	},
	{
		"fork": true,
		"name": "stone_placeDestroy",
		"max_db": 10
	},
	
	{
		"name": "snow",
		"list": [
			{
				"path": "sounds/snow/1.mp3"
			},
			{
				"path": "sounds/snow/2.mp3"
			},
			{
				"path": "sounds/snow/3.mp3"
			}
		],
		"playback_mode": 0,
		"random_pitch": 1.2,
		"random_volume_offset_db": 3,
		"max_db": 2
	},
	{
		"fork": true,
		"name": "snow_placeDestroy",
		"max_db": 6
	},
	
	
	{
		"name": "metal",
		"list": [
			{
				"path": "sounds/metal/1.mp3",
				"weight": 1
			},
			{
				"path": "sounds/metal/2.mp3",
				"weight": 1
			},
			{
				"path": "sounds/metal/3.mp3",
				"weight": 1
			},
			{
				"path": "sounds/metal/4.mp3",
				"weight": 1
			}
		],
		"playback_mode": 0,
		"random_pitch": 1.2,
		"random_volume_offset_db": 3,
		"max_db": 3
	},
	{
		"fork": true,
		"name": "metal_placeDestroy",
		"max_db": 10
	},
	
	
	{
		"name": "glass",
		"list": [
			{
				"path": "sounds/glass/1.mp3",
				"weight": 1
			}
		],
		"playback_mode": 0,
		"random_pitch": 1.2,
		"random_volume_offset_db": 3,
		"volume_db": -5,
		"max_db": 1
	},
	{
		"fork": true,
		"name": "glass_placeDestroy",
		"volume_db": -1,
		"max_db": 3
	},
	
	{
		"name": "wood",
		"list": [
			{
				"path": "sounds/wood/1.mp3"
			}
		],
		"playback_mode": 0,
		"random_pitch": 1.2,
		"random_volume_offset_db": 3
	},
	{
		"name": "wood_placeDestroy",
		"list": [
			{
				"path": "sounds/wood/build/1.mp3"
			},
			{
				"path": "sounds/wood/build/2.mp3"
			}
		],
		"playback_mode": 0,
		"random_pitch": 1.2,
		"random_volume_offset_db": 3
	},
	
	
	{
		"name": "explosion",
		"list": [
			{
				"path": "sounds/explosion/1.mp3",
				"weight": 1
			},
			{
				"path": "sounds/explosion/2.mp3",
				"weight": 1
			}
		],
		"playback_mode": 0,
		"unit_size": 64,
		"max_distance": 1000,
		"random_pitch": 1.2,
		"random_volume_offset_db": 3,
		"volume_db": 10,
		"max_db": 20
	},
	
	{
		"name": "indestructible",
		"list": [
			{
				"path": "sounds/indestructible.wav",
			}
		]
	}
]
